{
  "last_updated": "2026-05-03T07:48:58+00:00",
  "added": [
    "MAGS"
  ],
  "rejected": [
    {
      "ticker": "PLTR",
      "reason": "ticker already exists in tickers.json"
    },
    {
      "ticker": "RKLB",
      "reason": "ticker already exists in tickers.json"
    }
  ],
  "pending": [],
  "invalid": [
    {
      "ticker": "PLTR",
      "reason": "ticker already exists in tickers.json"
    },
    {
      "ticker": "RKLB",
      "reason": "ticker already exists in tickers.json"
    }
  ]
}
